gimp_mcp/__init__.py
gimp_mcp/gimp_api.py
gimp_mcp/mode_manager.py
gimp_mcp/server.py
gimp_mcp/resources/__init__.py
gimp_mcp/resources/providers.py
gimp_mcp/tools/__init__.py
gimp_mcp/tools/color_tools.py
gimp_mcp/tools/document_tools.py
gimp_mcp/tools/drawing_tools.py
gimp_mcp/tools/filter_tools.py
gimp_mcp/tools/layer_tools.py
gimp_mcp/tools/selection_tools.py
gimp_mcp/utils/__init__.py
gimp_mcp/utils/errors.py
gimp_mcp/utils/gi_helpers.py
gimp_mcp/utils/image_utils.py
gimp_mcp/utils/logging.py
gimp_mcp_server-0.1.0.dist-info/licenses/LICENSE
gimp_mcp_server-0.1.0.dist-info/METADATA
gimp_mcp_server-0.1.0.dist-info/WHEEL
gimp_mcp_server-0.1.0.dist-info/entry_points.txt
gimp_mcp_server-0.1.0.dist-info/top_level.txt
gimp_mcp_server-0.1.0.dist-info/RECORD
