Metadata-Version: 2.4
Name: gimp-mcp-server
Version: 0.1.0
Summary: MCP Server for GIMP - AI Assistant for Image Editing
Author-email: GIMP MCP Server Team <support@gimp-mcp.com>
License: MIT
Project-URL: Homepage, https://github.com/slliws/gimp-mcp-server
Project-URL: Documentation, https://github.com/slliws/gimp-mcp-server/blob/main/docs/README.md
Project-URL: Repository, https://github.com/slliws/gimp-mcp-server
Project-URL: Bug Tracker, https://github.com/slliws/gimp-mcp-server/issues
Keywords: mcp,gimp,ai,image-editing,graphics
Classifier: Development Status :: 3 - Alpha
Classifier: Intended Audience :: Developers
Classifier: Intended Audience :: End Users/Desktop
Classifier: License :: OSI Approved :: MIT License
Classifier: Operating System :: OS Independent
Classifier: Programming Language :: Python :: 3
Classifier: Programming Language :: Python :: 3.9
Classifier: Programming Language :: Python :: 3.10
Classifier: Programming Language :: Python :: 3.11
Classifier: Programming Language :: Python :: 3.12
Classifier: Topic :: Multimedia :: Graphics
Classifier: Topic :: Software Development :: Libraries :: Python Modules
Requires-Python: >=3.9
License-File: LICENSE
Requires-Dist: fastmcp>=0.1.0
Requires-Dist: mcp>=1.0.0
Requires-Dist: PyGObject>=3.42.0
Requires-Dist: Pillow>=9.0.0
Requires-Dist: numpy>=1.21.0
Requires-Dist: pydantic>=2.0.0
Requires-Dist: structlog>=22.0.0
Requires-Dist: typing-extensions>=4.0.0
Provides-Extra: dev
Requires-Dist: pytest>=7.0.0; extra == "dev"
Requires-Dist: pytest-asyncio>=0.21.0; extra == "dev"
Requires-Dist: pytest-cov>=4.0.0; extra == "dev"
Requires-Dist: pytest-mock>=3.10.0; extra == "dev"
Requires-Dist: black>=22.0.0; extra == "dev"
Requires-Dist: flake8>=6.0.0; extra == "dev"
Requires-Dist: mypy>=1.0.0; extra == "dev"
Requires-Dist: isort>=5.10.0; extra == "dev"
Dynamic: license-file
